fastapi_utils/__init__.py
fastapi_utils/api_model.py
fastapi_utils/api_settings.py
fastapi_utils/camelcase.py
fastapi_utils/cbv.py
fastapi_utils/enums.py
fastapi_utils/guid_type.py
fastapi_utils/inferring_router.py
fastapi_utils/openapi.py
fastapi_utils/py.typed
fastapi_utils/session.py
fastapi_utils/tasks.py
fastapi_utils/timing.py
fastapi_utils-0.2.0.dist-info/LICENSE
fastapi_utils-0.2.0.dist-info/WHEEL
fastapi_utils-0.2.0.dist-info/METADATA
fastapi_utils-0.2.0.dist-info/RECORD
