Metadata-Version: 2.1
Name: fastapi-utils
Version: 0.2.0
Summary: Reusable utilities for FastAPI
Home-page: https://fastapi-utils.davidmontague.xyz
License: MIT
Keywords: fastapi,utilities,utils
Author: David Montague
Author-email: davwmont@gmail.com
Requires-Python: >=3.6,<4.0
Classifier: Development Status :: 3 - Alpha
Classifier: Environment :: Web Environment
Classifier: Framework :: AsyncIO
Classifier: Intended Audience :: Developers
Classifier: Intended Audience :: Information Technology
Classifier: Intended Audience :: System Administrators
Classifier: License :: OSI Approved :: MIT License
Classifier: Operating System :: OS Independent
Classifier: Programming Language :: Python
Classifier: Programming Language :: Python :: 3
Classifier: Programming Language :: Python :: 3 :: Only
Classifier: Programming Language :: Python :: 3.6
Classifier: Programming Language :: Python :: 3.7
Classifier: Programming Language :: Python :: 3.8
Classifier: Topic :: Internet
Classifier: Topic :: Internet :: WWW/HTTP
Classifier: Topic :: Internet :: WWW/HTTP :: HTTP Servers
Classifier: Topic :: Software Development
Classifier: Topic :: Software Development :: Libraries
Classifier: Topic :: Software Development :: Libraries :: Python Modules
Classifier: Topic :: Utilities
Classifier: Typing :: Typed
Requires-Dist: fastapi
Requires-Dist: pydantic (>=1.0,<2.0)
Requires-Dist: sqlalchemy (>=1.3.12,<2.0.0)
Project-URL: Documentation, https://fastapi-utils.davidmontague.xyz
Project-URL: Repository, https://github.com/dmontagu/fastapi-utils
